Metadata-Version: 2.1
Name: odoo-addon-membership_prorate_variable_period
Version: 18.0.1.0.1
Requires-Python: >=3.10
Requires-Dist: odoo-addon-membership_prorate==18.0.*
Requires-Dist: odoo-addon-membership_variable_period==18.0.*
Requires-Dist: odoo==18.0.*
Summary: Prorate membership fee for variable periods
Home-page: https://github.com/OCA/vertical-association
License: AGPL-3
Author: Tecnativa, Odoo Community Association (OCA)
Author-email: support@odoo-community.org
Classifier: Programming Language :: Python
Classifier: Framework :: Odoo
Classifier: Framework :: Odoo :: 18.0
Classifier: License :: OSI Approved :: GNU Affero General Public License v3
